gyna/__init__.py
gyna/__main__.py
gyna/_cli/__init__.py
gyna/_cli/argparse.py
gyna/command/__init__.py
gyna/command/run.py
gyna/test/__init__.py
gyna-0.0.1.dist-info/METADATA
gyna-0.0.1.dist-info/WHEEL
gyna-0.0.1.dist-info/RECORD
