Metadata-Version: 2.3
Name: gyna
Version: 0.0.1
Summary: 
License: BSD 3-clause
Author: Nicolas Despres
Requires-Python: >=3.12
Classifier: License :: Other/Proprietary License
Classifier: Programming Language :: Python :: 3
Classifier: Programming Language :: Python :: 3.12
Classifier: Programming Language :: Python :: 3.13
Requires-Dist: pyglet (==2.1.6)
